novig/__init__.py
novig/models.py
novig/novig_api.py
novig/novig_base.py
novig_liquidity-1.0.8.dist-info/METADATA
novig_liquidity-1.0.8.dist-info/WHEEL
novig_liquidity-1.0.8.dist-info/top_level.txt
novig_liquidity-1.0.8.dist-info/RECORD
