Metadata-Version: 2.4
Name: novig_liquidity
Version: 1.0.8
Summary: A Python wrapper for the Novig API with built-in filtering and liquidity validation.
Home-page: https://github.com/Hurteau101/Novig_Liquidity_Template
Author: Devon H
License: MIT
Requires-Python: >=3.8
Requires-Dist: aiohappyeyeballs==2.6.1
Requires-Dist: aiohttp==3.12.15
Requires-Dist: aiosignal==1.4.0
Requires-Dist: annotated-types==0.7.0
Requires-Dist: attrs==25.3.0
Requires-Dist: certifi==2025.8.3
Requires-Dist: charset-normalizer==3.4.3
Requires-Dist: frozenlist==1.7.0
Requires-Dist: idna==3.10
Requires-Dist: multidict==6.6.4
Requires-Dist: propcache==0.3.2
Requires-Dist: pydantic==2.11.9
Requires-Dist: pydantic_core==2.33.2
Requires-Dist: redis==6.4.0
Requires-Dist: requests==2.32.5
Requires-Dist: typing-inspection==0.4.1
Requires-Dist: typing_extensions==4.15.0
Requires-Dist: urllib3==2.5.0
Requires-Dist: yarl==1.20.1
Dynamic: author
Dynamic: description
Dynamic: description-content-type
Dynamic: home-page
Dynamic: license
Dynamic: requires-dist
Dynamic: requires-python
Dynamic: summary
